fotools/__init__.py
fotools/extensions.py
fotools/help.py
fotools/installed_extensions/__init__.py
fotools/installed_extensions/delete.py
fotools/installed_extensions/pcloud_upload.py
fotools/installed_extensions/search_contents.py
fotools/installed_extensions/testextension.py
fotools/installed_extensions/testextension2.py
fotools/main.py
fotools/organizer.py
fotools/parser.py
fotools-0.1.2.dist-info/entry_points.txt
fotools-0.1.2.dist-info/LICENSE
fotools-0.1.2.dist-info/WHEEL
fotools-0.1.2.dist-info/METADATA
fotools-0.1.2.dist-info/RECORD
