Metadata-Version: 2.1
Name: fotools
Version: 0.1.2
Summary: Tool for searching and organizing files
Home-page: https://github.com/matt-wisdom/file_organizer
License: BSD 3-Clause License
Author: Matthew Wisdom
Author-email: matthewwisdom11@gmail.com
Requires-Python: >=3.9,<4.0
Classifier: License :: Other/Proprietary License
Classifier: Programming Language :: Python :: 3
Classifier: Programming Language :: Python :: 3.9
Classifier: Programming Language :: Python :: 3.10
Classifier: Programming Language :: Python :: 3.11
Requires-Dist: bandit (>=1.7.4,<2.0.0)
Requires-Dist: filetype (>=1.0.13,<2.0.0)
Requires-Dist: python-Levenshtein (>=0.20.8,<0.21.0)
Requires-Dist: rapidfuzz (>=2.13.1,<3.0.0)
Project-URL: Repository, https://github.com/matt-wisdom/file_organizer
